{
	"configurations" : 
	[
		{
			"directories" : 
			[
				{
					"build" : ".",
					"hasInstallRule" : true,
					"jsonFile" : "directory-.-449c88ac2c40765913ca.json",
					"minimumCMakeVersion" : 
					{
						"string" : "3.12"
					},
					"projectIndex" : 0,
					"source" : ".",
					"targetIndexes" : 
					[
						0,
						1
					]
				}
			],
			"name" : "",
			"projects" : 
			[
				{
					"directoryIndexes" : 
					[
						0
					],
					"name" : "amr_description",
					"targetIndexes" : 
					[
						0,
						1
					]
				}
			],
			"targets" : 
			[
				{
					"directoryIndex" : 0,
					"id" : "amr_description_uninstall::@6890427a1f51a3e7e1df",
					"jsonFile" : "target-amr_description_uninstall-e7decf129050f6fd8029.json",
					"name" : "amr_description_uninstall",
					"projectIndex" : 0
				},
				{
					"directoryIndex" : 0,
					"id" : "uninstall::@6890427a1f51a3e7e1df",
					"jsonFile" : "target-uninstall-1758c766eb97745fdd5a.json",
					"name" : "uninstall",
					"projectIndex" : 0
				}
			]
		}
	],
	"kind" : "codemodel",
	"paths" : 
	{
		"build" : "/home/huyjetson/mobile_robot/ros2_ws/build/amr_description",
		"source" : "/home/huyjetson/mobile_robot/ros2_ws/src/amr_description"
	},
	"version" : 
	{
		"major" : 2,
		"minor" : 3
	}
}
